geoengine_openapi_client/__init__.py
geoengine_openapi_client/api_client.py
geoengine_openapi_client/api_response.py
geoengine_openapi_client/configuration.py
geoengine_openapi_client/exceptions.py
geoengine_openapi_client/py.typed
geoengine_openapi_client/rest.py
geoengine_openapi_client/api/__init__.py
geoengine_openapi_client/api/datasets_api.py
geoengine_openapi_client/api/general_api.py
geoengine_openapi_client/api/layers_api.py
geoengine_openapi_client/api/ml_api.py
geoengine_openapi_client/api/ogcwcs_api.py
geoengine_openapi_client/api/ogcwfs_api.py
geoengine_openapi_client/api/ogcwms_api.py
geoengine_openapi_client/api/permissions_api.py
geoengine_openapi_client/api/plots_api.py
geoengine_openapi_client/api/projects_api.py
geoengine_openapi_client/api/session_api.py
geoengine_openapi_client/api/spatial_references_api.py
geoengine_openapi_client/api/tasks_api.py
geoengine_openapi_client/api/uploads_api.py
geoengine_openapi_client/api/user_api.py
geoengine_openapi_client/api/workflows_api.py
geoengine_openapi_client/models/__init__.py
geoengine_openapi_client/models/add_dataset.py
geoengine_openapi_client/models/add_layer.py
geoengine_openapi_client/models/add_layer_collection.py
geoengine_openapi_client/models/add_role.py
geoengine_openapi_client/models/aruna_data_provider_definition.py
geoengine_openapi_client/models/auth_code_request_url.py
geoengine_openapi_client/models/auth_code_response.py
geoengine_openapi_client/models/auto_create_dataset.py
geoengine_openapi_client/models/axis_order.py
geoengine_openapi_client/models/bounding_box2_d.py
geoengine_openapi_client/models/breakpoint.py
geoengine_openapi_client/models/classification_measurement.py
geoengine_openapi_client/models/collection_item.py
geoengine_openapi_client/models/collection_type.py
geoengine_openapi_client/models/color_param.py
geoengine_openapi_client/models/colorizer.py
geoengine_openapi_client/models/computation_quota.py
geoengine_openapi_client/models/continuous_measurement.py
geoengine_openapi_client-0.0.30.dist-info/METADATA
geoengine_openapi_client-0.0.30.dist-info/WHEEL
geoengine_openapi_client-0.0.30.dist-info/top_level.txt
geoengine_openapi_client-0.0.30.dist-info/RECORD
