Metadata-Version: 2.4
Name: geoengine_openapi_client
Version: 0.0.30
Summary: Geo Engine API
Home-page: https://github.com/geo-engine/openapi-client
Author: Geo Engine Developers
Author-email: Geo Engine Developers <dev@geoengine.de>
License: Apache-2.0
Project-URL: Repository, https://github.com/GIT_USER_ID/GIT_REPO_ID
Keywords: OpenAPI,OpenAPI-Generator,Geo Engine API
Requires-Python: >=3.9
Requires-Dist: urllib3<3.0.0,>=2.1.0
Requires-Dist: python-dateutil>=2.8.2
Requires-Dist: pydantic>=2
Requires-Dist: typing-extensions>=4.7.1
Dynamic: author
Dynamic: home-page
